minieval/cli.py
minieval/datatypes.py
minieval/few_shot.py
minieval/formatters.py
minieval/metrics.py
minieval/task_registry.py
minieval/utils.py
minieval/backends/__init__.py
minieval/backends/litellm.py
minieval/backends/mock.py
minieval/backends/ollama.py
minieval/backends/vllm.py
minieval/execute/local_python.py
minieval/extract/code.py
minieval/extract/math_latex.py
minieval/extract/qa.py
minieval/launchers/__init__.py
minieval/launchers/beaker/constants.py
minieval/launchers/beaker/defaults.py
minieval/launchers/beaker/launcher.py
minieval/score/core.py
minieval/tasks/aime.py
minieval/tasks/arc.py
minieval/tasks/gpqa.py
minieval/tasks/gsm.py
minieval/tasks/hellaswag.py
minieval/tasks/minerva.py
minieval/tasks/mmlu.py
minieval/writers/datalake.py
minieval/writers/legacy_datalake.py
minieval-0.2.0.dist-info/METADATA
minieval-0.2.0.dist-info/WHEEL
minieval-0.2.0.dist-info/entry_points.txt
minieval-0.2.0.dist-info/top_level.txt
minieval-0.2.0.dist-info/RECORD
