Metadata-Version: 2.4
Name: minieval
Version: 0.2.0
Requires-Python: >=3.10
Requires-Dist: datasets
Requires-Dist: rich
Requires-Dist: omegaconf
Requires-Dist: jinja2
Requires-Dist: sympy
Requires-Dist: cloudpickle
Provides-Extra: dev
Requires-Dist: ruff; extra == "dev"
Requires-Dist: mypy<1.4,>=1.0; extra == "dev"
Requires-Dist: black<24.0,>=23.1; extra == "dev"
Requires-Dist: isort<5.14,>=5.12; extra == "dev"
Requires-Dist: build; extra == "dev"
Requires-Dist: twine>=1.11.0; extra == "dev"
Provides-Extra: beaker
Requires-Dist: beaker-py>=2.0; extra == "beaker"
Requires-Dist: GitPython<4.0,>=3.0; extra == "beaker"
Requires-Dist: beaker-gantry; extra == "beaker"
Provides-Extra: vllm
Requires-Dist: vllm==0.9.2; extra == "vllm"
Provides-Extra: litellm
Requires-Dist: litellm>=1.0.0; extra == "litellm"
Requires-Dist: requests; extra == "litellm"
Requires-Dist: aiohttp; extra == "litellm"
Provides-Extra: ollama
Requires-Dist: ollama>=0.1.0; extra == "ollama"
Provides-Extra: all
Requires-Dist: minieval[beaker,dev,litellm,ollama,vllm]; extra == "all"
